{
    "id": "org.kde.kiten",
    "runtime": "org.kde.Platform",
    "runtime-version": "5.15-21.08",
    "sdk": "org.kde.Sdk",
    "command": "kiten",
    "rename-icon": "kiten",
    "finish-args": [
        "--share=ipc",
        "--socket=x11",
        "--socket=wayland",
        "--device=dri"
    ],

    "modules": [
        {
            "name": "kiten",
            "buildsystem": "cmake-ninja",
            "sources": [
                { 
                    "type": "archive", 
                    "url": "https://download.kde.org/stable/release-service/21.12.1/src/kiten-21.12.1.tar.xz",
                    "sha256": "4c159e80be6c5672ff83eab9cca470acc1884b62c9a74414ab3de97b52263424"
                }                 
            ]
        }
    ]
}
